tests/__init__.py
tests/serializers_tests.py
tests/test_classifier.py
tests/test_clusters.py
tests/test_external.py
tests/test_lda.py
tests/test_lexicon.py
tests/test_phrases.py
tests/test_w2v.py
tests/tests.py
text_analytics/__init__.py
text_analytics/helpers.py
text_analytics/loader.py
text_analytics/serializers.py
text_analytics/settings.py
text_analytics/text_analytics.py
textanalytics-1.1.dist-info/LICENSE
textanalytics-1.1.dist-info/METADATA
textanalytics-1.1.dist-info/WHEEL
textanalytics-1.1.dist-info/top_level.txt
textanalytics-1.1.dist-info/RECORD
