Metadata-Version: 2.1
Name: textanalytics
Version: 1.1
Summary: Basic computational linguistics and natural language processing in Python
Home-page: https://github.com/jonathandunn/text_analytics
Author: Jonathan Dunn
Author-email: jonathan.dunn@canterbury.ac.nz
License: GNU GENERAL PUBLIC LICENSE v3
Keywords: text analytics,natural language processing,computational linguistics
Platform: UNKNOWN
License-File: LICENSE
Requires-Dist: cytoolz
Requires-Dist: gensim (>=4.0)
Requires-Dist: numpy
Requires-Dist: pandas
Requires-Dist: scipy
Requires-Dist: scikit-learn (>=0.24.0)
Requires-Dist: tensorflow (>=2.0)
Requires-Dist: spacy (>=3.0)
Requires-Dist: wordcloud
Requires-Dist: matplotlib
Requires-Dist: seaborn
Requires-Dist: requests
Requires-Dist: stop-words
Requires-Dist: boto3
Requires-Dist: tqdm
Requires-Dist: c2xg (>=1.0)
Requires-Dist: corpus-similarity (>=1.0)
Requires-Dist: clean-text
